AUTHORS.rst
LICENSE
MANIFEST.in
README.rst
setup.py
django_pycharm_breakpoint/__init__.py
django_pycharm_breakpoint/django_app.py
django_pycharm_breakpoint.egg-info/PKG-INFO
django_pycharm_breakpoint.egg-info/SOURCES.txt
django_pycharm_breakpoint.egg-info/dependency_links.txt
django_pycharm_breakpoint.egg-info/not-zip-safe
django_pycharm_breakpoint.egg-info/requires.txt
django_pycharm_breakpoint.egg-info/top_level.txt