Metadata-Version: 1.1
Name: django-pycharm-breakpoint
Version: 0.3.0
Summary: App for Django to during development enter PyCharm debugger on uncaught exceptions
Home-page: https://github.com/jlubcke/django-pycharm-breakpoint
Author: Johan Lübcke
Author-email: johan@lubcke.se
License: BSD
Keywords: Django,pycharm
Platform: UNKNOWN
Classifier: Development Status :: 5 - Production/Stable
Classifier: Intended Audience :: Developers
Classifier: License :: OSI Approved :: BSD License
Classifier: Natural Language :: English
Classifier: Operating System :: POSIX
Classifier: Operating System :: Microsoft :: Windows
Classifier: Operating System :: MacOS :: MacOS X
Classifier: Topic :: Software Development :: Testing
Classifier: Topic :: Software Development :: Libraries
Classifier: Topic :: Utilities
Classifier: Programming Language :: Python :: 3
Classifier: Programming Language :: Python :: 3.7
Classifier: Programming Language :: Python :: 3.8
